odoo/addons/product_category_code_unique/README.rst
odoo/addons/product_category_code_unique/__init__.py
odoo/addons/product_category_code_unique/__manifest__.py
odoo/addons/product_category_code_unique/hooks.py
odoo/addons/product_category_code_unique/data/product_category_sequence.xml
odoo/addons/product_category_code_unique/i18n/es.po
odoo/addons/product_category_code_unique/i18n/it.po
odoo/addons/product_category_code_unique/i18n/product_category_code_unique.pot
odoo/addons/product_category_code_unique/models/__init__.py
odoo/addons/product_category_code_unique/models/product_category.py
odoo/addons/product_category_code_unique/readme/CONTRIBUTORS.rst
odoo/addons/product_category_code_unique/readme/DESCRIPTION.rst
odoo/addons/product_category_code_unique/static/description/icon.png
odoo/addons/product_category_code_unique/static/description/index.html
odoo/addons/product_category_code_unique/tests/__init__.py
odoo/addons/product_category_code_unique/tests/test_code_unique.py
odoo14_addon_product_category_code_unique-14.0.1.0.1.dev8.dist-info/METADATA
odoo14_addon_product_category_code_unique-14.0.1.0.1.dev8.dist-info/WHEEL
odoo14_addon_product_category_code_unique-14.0.1.0.1.dev8.dist-info/top_level.txt
odoo14_addon_product_category_code_unique-14.0.1.0.1.dev8.dist-info/RECORD
